aiohttp_spotify/__init__.py
aiohttp_spotify/aiohttp_spotify_version.py
aiohttp_spotify/api.py
aiohttp_spotify/app.py
aiohttp_spotify/mock_api.py
aiohttp_spotify/views.py
aiohttp_spotify-0.0.4.dist-info/LICENSE
aiohttp_spotify-0.0.4.dist-info/METADATA
aiohttp_spotify-0.0.4.dist-info/WHEEL
aiohttp_spotify-0.0.4.dist-info/top_level.txt
aiohttp_spotify-0.0.4.dist-info/RECORD
