Metadata-Version: 2.1
Name: aiohttp-spotify
Version: 0.0.4
Summary: An async Python interface to the Spotify API using aiohttp
Home-page: https://github.com/dfm/aiohttp_spotify
Author: Daniel Foreman-Mackey
Author-email: foreman.mackey@gmail.com
Maintainer: Daniel Foreman-Mackey
Maintainer-email: foreman.mackey@gmail.com
License: MIT
Platform: UNKNOWN
Classifier: Development Status :: 3 - Alpha
Classifier: Intended Audience :: Developers
Classifier: License :: OSI Approved :: MIT License
Classifier: Operating System :: OS Independent
Classifier: Programming Language :: Python
Classifier: Programming Language :: Python :: 3
Requires-Dist: aiohttp
